pysindy/__init__.py
pysindy/pysindy.py
pysindy/version.py
pysindy/deeptime/__init__.py
pysindy/deeptime/deeptime.py
pysindy/differentiation/__init__.py
pysindy/differentiation/base.py
pysindy/differentiation/finite_difference.py
pysindy/differentiation/sindy_derivative.py
pysindy/differentiation/smoothed_finite_difference.py
pysindy/differentiation/spectral_derivative.py
pysindy/feature_library/__init__.py
pysindy/feature_library/base.py
pysindy/feature_library/custom_library.py
pysindy/feature_library/fourier_library.py
pysindy/feature_library/generalized_library.py
pysindy/feature_library/identity_library.py
pysindy/feature_library/parameterized_library.py
pysindy/feature_library/pde_library.py
pysindy/feature_library/polynomial_library.py
pysindy/feature_library/sindy_pi_library.py
pysindy/feature_library/weak_pde_library.py
pysindy/optimizers/__init__.py
pysindy/optimizers/base.py
pysindy/optimizers/constrained_sr3.py
pysindy/optimizers/frols.py
pysindy/optimizers/miosr.py
pysindy/optimizers/sindy_optimizer.py
pysindy/optimizers/sindy_pi.py
pysindy/optimizers/sr3.py
pysindy/optimizers/ssr.py
pysindy/optimizers/stable_linear_sr3.py
pysindy/optimizers/stlsq.py
pysindy/optimizers/trapping_sr3.py
pysindy/utils/__init__.py
pysindy/utils/axes.py
pysindy/utils/base.py
pysindy/utils/odes.py
pysindy-1.7.5.dist-info/LICENSE
pysindy-1.7.5.dist-info/METADATA
pysindy-1.7.5.dist-info/WHEEL
pysindy-1.7.5.dist-info/top_level.txt
pysindy-1.7.5.dist-info/RECORD
