Metadata-Version: 2.1
Name: pysindy
Version: 1.7.5
Summary: Sparse Identification of Nonlinear Dynamics
Home-page: https://github.com/dynamicslab/pysindy
Author: Brian de Silva, Kathleen Champion, Markus Quade, Alan Kaptanoglu
Author-email: bdesilva@uw.edu, kpchamp@uw.edu, info@markusqua.de, akaptano@uw.edu
License: MIT
Platform: UNKNOWN
Classifier: Programming Language :: Python
Classifier: Programming Language :: Python :: 3.7
Classifier: Programming Language :: Python :: 3.8
Classifier: Programming Language :: Python :: 3.9
Classifier: Programming Language :: Python :: 3.10
Classifier: Development Status :: 5 - Production/Stable
Classifier: Intended Audience :: Science/Research
Classifier: License :: OSI Approved :: MIT License
Classifier: Topic :: Scientific/Engineering :: Mathematics
Requires-Python: >=3.7
Provides-Extra: miosr
